cycad.py
cycad-1.1.1.dist-info/LICENSE
cycad-1.1.1.dist-info/METADATA
cycad-1.1.1.dist-info/WHEEL
cycad-1.1.1.dist-info/top_level.txt
cycad-1.1.1.dist-info/RECORD
