Metadata-Version: 2.1
Name: cycad
Version: 1.1.1
Summary: CYCling Autocorrelation Dataviz
Author: Yue Wu
Classifier: Programming Language :: Python :: 3
Classifier: License :: OSI Approved :: MIT License
Classifier: Operating System :: OS Independent
Requires-Python: >=3.6
License-File: LICENSE
Requires-Dist: numpy
Requires-Dist: pandas
Requires-Dist: matplotlib
Requires-Dist: charset-normalizer
Requires-Dist: scipy
Requires-Dist: tqdm
Requires-Dist: h5py
